Metadata-Version: 2.1
Name: Kivy-jetson
Version: 2.1.0.dev0
Summary: A software library for rapid development of hardware-accelerated multitouch applications.
Home-page: http://kivy.org
Author: Kivy Team and other contributors
Author-email: kivy-dev@googlegroups.com
License: MIT
Platform: UNKNOWN
Classifier: Development Status :: 5 - Production/Stable
Classifier: Environment :: MacOS X
Classifier: Environment :: Win32 (MS Windows)
Classifier: Environment :: X11 Applications
Classifier: Intended Audience :: Developers
Classifier: Intended Audience :: End Users/Desktop
Classifier: Intended Audience :: Information Technology
Classifier: Intended Audience :: Science/Research
Classifier: License :: OSI Approved :: MIT License
Classifier: Natural Language :: English
Classifier: Operating System :: MacOS :: MacOS X
Classifier: Operating System :: Microsoft :: Windows
Classifier: Operating System :: POSIX :: BSD :: FreeBSD
Classifier: Operating System :: POSIX :: Linux
Classifier: Programming Language :: Python :: 3.6
Classifier: Programming Language :: Python :: 3.7
Classifier: Programming Language :: Python :: 3.8
Classifier: Programming Language :: Python :: 3.9
Classifier: Topic :: Artistic Software
Classifier: Topic :: Games/Entertainment
Classifier: Topic :: Multimedia :: Graphics :: 3D Rendering
Classifier: Topic :: Multimedia :: Graphics :: Capture :: Digital Camera
Classifier: Topic :: Multimedia :: Graphics :: Presentation
Classifier: Topic :: Multimedia :: Graphics :: Viewers
Classifier: Topic :: Multimedia :: Sound/Audio :: Players :: MP3
Classifier: Topic :: Multimedia :: Video :: Display
Classifier: Topic :: Scientific/Engineering :: Human Machine Interfaces
Classifier: Topic :: Scientific/Engineering :: Visualization
Classifier: Topic :: Software Development :: Libraries :: Application Frameworks
Classifier: Topic :: Software Development :: User Interfaces
Requires-Python: >=3.6
Requires-Dist: Kivy-Garden (>=0.1.4)
Requires-Dist: docutils
Requires-Dist: pygments
Requires-Dist: kivy-deps.angle (~=0.3.0) ; sys_platform == "win32"
Requires-Dist: kivy-deps.sdl2 (~=0.3.1) ; sys_platform == "win32"
Requires-Dist: kivy-deps.glew (~=0.3.0) ; sys_platform == "win32"
Requires-Dist: pypiwin32 ; sys_platform == "win32"
Provides-Extra: angle
Requires-Dist: kivy-deps.angle (~=0.3.0) ; (sys_platform == "win32") and extra == 'angle'
Provides-Extra: base
Requires-Dist: pillow ; extra == 'base'
Requires-Dist: docutils ; extra == 'base'
Requires-Dist: pygments ; extra == 'base'
Requires-Dist: kivy-deps.angle (~=0.3.0) ; (sys_platform == "win32") and extra == 'base'
Requires-Dist: kivy-deps.sdl2 (~=0.3.1) ; (sys_platform == "win32") and extra == 'base'
Requires-Dist: kivy-deps.glew (~=0.3.0) ; (sys_platform == "win32") and extra == 'base'
Requires-Dist: pypiwin32 ; (sys_platform == "win32") and extra == 'base'
Provides-Extra: dev
Requires-Dist: pytest (>=3.6) ; extra == 'dev'
Requires-Dist: pytest-cov ; extra == 'dev'
Requires-Dist: pytest-asyncio (!=0.11.0) ; extra == 'dev'
Requires-Dist: pytest-timeout ; extra == 'dev'
Requires-Dist: pytest-benchmark ; extra == 'dev'
Requires-Dist: pyinstaller ; extra == 'dev'
Requires-Dist: sphinx ; extra == 'dev'
Requires-Dist: sphinxcontrib-blockdiag ; extra == 'dev'
Requires-Dist: sphinxcontrib-seqdiag ; extra == 'dev'
Requires-Dist: sphinxcontrib-actdiag ; extra == 'dev'
Requires-Dist: sphinxcontrib-nwdiag ; extra == 'dev'
Requires-Dist: flake8 ; extra == 'dev'
Requires-Dist: pre-commit ; extra == 'dev'
Requires-Dist: kivy-deps.gstreamer-dev (~=0.3.1) ; (sys_platform == "win32") and extra == 'dev'
Requires-Dist: kivy-deps.sdl2-dev (~=0.3.1) ; (sys_platform == "win32") and extra == 'dev'
Requires-Dist: kivy-deps.glew-dev (~=0.3.0) ; (sys_platform == "win32") and extra == 'dev'
Provides-Extra: full
Requires-Dist: pillow ; extra == 'full'
Requires-Dist: docutils ; extra == 'full'
Requires-Dist: pygments ; extra == 'full'
Requires-Dist: ffpyplayer ; (sys_platform == "linux" or sys_platform == "darwin") and extra == 'full'
Requires-Dist: kivy-deps.gstreamer (~=0.3.1) ; (sys_platform == "win32") and extra == 'full'
Requires-Dist: kivy-deps.angle (~=0.3.0) ; (sys_platform == "win32") and extra == 'full'
Requires-Dist: kivy-deps.sdl2 (~=0.3.1) ; (sys_platform == "win32") and extra == 'full'
Requires-Dist: kivy-deps.glew (~=0.3.0) ; (sys_platform == "win32") and extra == 'full'
Requires-Dist: pypiwin32 ; (sys_platform == "win32") and extra == 'full'
Provides-Extra: glew
Requires-Dist: kivy-deps.glew (~=0.3.0) ; (sys_platform == "win32") and extra == 'glew'
Provides-Extra: gstreamer
Requires-Dist: kivy-deps.gstreamer (~=0.3.1) ; (sys_platform == "win32") and extra == 'gstreamer'
Provides-Extra: media
Requires-Dist: ffpyplayer ; (sys_platform == "linux" or sys_platform == "darwin") and extra == 'media'
Requires-Dist: kivy-deps.gstreamer (~=0.3.1) ; (sys_platform == "win32") and extra == 'media'
Provides-Extra: sdl2
Requires-Dist: kivy-deps.sdl2 (~=0.3.1) ; (sys_platform == "win32") and extra == 'sdl2'
Provides-Extra: tuio
Requires-Dist: oscpy ; extra == 'tuio'
